peaksjs_widget/__init__.py
peaksjs_widget/_frontend.py
peaksjs_widget/_version.py
peaksjs_widget/widget.py
peaksjs_widget/labextension/package.json
peaksjs_widget/labextension/static/122.7fe735b33ffba8d22321.js
peaksjs_widget/labextension/static/228.da76ebea4a60315108d5.js
peaksjs_widget/labextension/static/317.028b6e2784f01fef0215.js
peaksjs_widget/labextension/static/509.3f8bcb120307cd5c9f73.js
peaksjs_widget/labextension/static/692.430ea81024d8312c4c52.js
peaksjs_widget/labextension/static/692.430ea81024d8312c4c52.js.LICENSE.txt
peaksjs_widget/labextension/static/778.9b5dc2348240296c4f3e.js
peaksjs_widget/labextension/static/863.a0a71a17193b5076787e.js
peaksjs_widget/labextension/static/885.3d20b6b4be74bc797067.js
peaksjs_widget/labextension/static/remoteEntry.e8b650bbe00f27462ddf.js
peaksjs_widget/labextension/static/style.js
peaksjs_widget/labextension/static/third-party-licenses.json
peaksjs_widget/tests/__init__.py
peaksjs_widget/tests/conftest.py
peaksjs_widget/tests/test_example.py
peaksjs_widget/tests/test_nbextension_path.py
peaksjs_widget-0.2.1.data/data/share/jupyter/labextensions/peaksjs_widget/package.json
peaksjs_widget-0.2.1.data/data/share/jupyter/labextensions/peaksjs_widget/static/122.7fe735b33ffba8d22321.js
peaksjs_widget-0.2.1.data/data/share/jupyter/labextensions/peaksjs_widget/static/228.da76ebea4a60315108d5.js
peaksjs_widget-0.2.1.data/data/share/jupyter/labextensions/peaksjs_widget/static/317.028b6e2784f01fef0215.js
peaksjs_widget-0.2.1.data/data/share/jupyter/labextensions/peaksjs_widget/static/509.3f8bcb120307cd5c9f73.js
peaksjs_widget-0.2.1.data/data/share/jupyter/labextensions/peaksjs_widget/static/692.430ea81024d8312c4c52.js
peaksjs_widget-0.2.1.data/data/share/jupyter/labextensions/peaksjs_widget/static/692.430ea81024d8312c4c52.js.LICENSE.txt
peaksjs_widget-0.2.1.data/data/share/jupyter/labextensions/peaksjs_widget/static/778.9b5dc2348240296c4f3e.js
peaksjs_widget-0.2.1.dist-info/METADATA
peaksjs_widget-0.2.1.dist-info/WHEEL
peaksjs_widget-0.2.1.dist-info/licenses/LICENSE.txt
peaksjs_widget-0.2.1.dist-info/RECORD
