Metadata-Version: 2.4
Name: peaksjs_widget
Version: 0.2.1
Summary: ipywidget to interact with audio waveforms through peaks.js
Project-URL: Homepage, https://github.com/ktonal/peaksjs-widget
Author-email: AntoineDaurat <ktonalberlin@gmail.com>
License: Copyright (c) 2023 AntoineDaurat
License-File: LICENSE.txt
Keywords: IPython,Jupyter,Widgets
Classifier: Framework :: Jupyter
Classifier: Intended Audience :: Developers
Classifier: Intended Audience :: Science/Research
Classifier: License :: OSI Approved :: BSD License
Classifier: Programming Language :: Python
Classifier: Programming Language :: Python :: 3
Classifier: Programming Language :: Python :: 3.7
Classifier: Programming Language :: Python :: 3.8
Classifier: Programming Language :: Python :: 3.9
Classifier: Programming Language :: Python :: 3.10
Requires-Python: >=3.10
Requires-Dist: ipywidgets>=8.1.0
Requires-Dist: numpy
Requires-Dist: pydub
Provides-Extra: test
Requires-Dist: nbval; extra == 'test'
Requires-Dist: pytest-cov; extra == 'test'
Requires-Dist: pytest>=6.0; extra == 'test'
